clerk_backend_sdk/__init__.py
clerk_backend_sdk/api/__init__.py
clerk_backend_sdk/api/actor_tokens_api.py
clerk_backend_sdk/api/allow_list_block_list_api.py
clerk_backend_sdk/api/beta_features_api.py
clerk_backend_sdk/api/clients_api.py
clerk_backend_sdk/api/domains_api.py
clerk_backend_sdk/api/email_addresses_api.py
clerk_backend_sdk/api/email_sms_templates_api.py
clerk_backend_sdk/api/instance_settings_api.py
clerk_backend_sdk/api/invitations_api.py
clerk_backend_sdk/api/jwks_api.py
clerk_backend_sdk/api/jwt_templates_api.py
clerk_backend_sdk/api/miscellaneous_api.py
clerk_backend_sdk/api/o_auth_applications_api.py
clerk_backend_sdk/api/organization_invitations_api.py
clerk_backend_sdk/api/organization_memberships_api.py
clerk_backend_sdk/api/organizations_api.py
clerk_backend_sdk/api/phone_numbers_api.py
clerk_backend_sdk/api/proxy_checks_api.py
clerk_backend_sdk/api/redirect_urls_api.py
clerk_backend_sdk/api/saml_connections_api.py
clerk_backend_sdk/api/sessions_api.py
clerk_backend_sdk/api/sign_in_tokens_api.py
clerk_backend_sdk/api/sign_ups_api.py
clerk_backend_sdk/api/testing_tokens_api.py
clerk_backend_sdk/api/users_api.py
clerk_backend_sdk/api/webhooks_api.py
clerk_backend_sdk/api_client.py
clerk_backend_sdk/api_response.py
clerk_backend_sdk/configuration.py
clerk_backend_sdk/exceptions.py
clerk_backend_sdk/models/__init__.py
clerk_backend_sdk/models/actor_token.py
clerk_backend_sdk/models/add_domain_request.py
clerk_backend_sdk/models/admin.py
clerk_backend_sdk/models/allowlist_identifier.py
clerk_backend_sdk/models/blocklist_identifier.py
clerk_backend_sdk/models/blocklist_identifiers.py
clerk_backend_sdk/models/c_name_target.py
clerk_backend_sdk/models/change_production_instance_domain_request.py
clerk_backend_sdk/models/clerk_error.py
clerk_backend_sdk/models/clerk_errors.py
clerk_backend_sdk/models/client.py
clerk_backend_sdk/models/create_actor_token_request.py
clerk_backend_sdk/models/create_allowlist_identifier_request.py
clerk_backend_sdk-1.1.1.dist-info/METADATA
clerk_backend_sdk-1.1.1.dist-info/WHEEL
clerk_backend_sdk-1.1.1.dist-info/RECORD
